Workbook

Sheet How to use
A1: How to use this tracker
A2: Yellow cells are yours to fill in: Status (dropdown), Date contacted, Notes. 'Follow up on' calculates itself (date contacted + 7 days).
A3: Priority A = active business with a clear website problem or no website. B = smaller opportunity. Goodwill = no pitch, just a helpful heads-up. C = only old directory listings, may not be operating. Rows marked 'EMAIL DRAFTED' in Notes have emails ready from our chat.
A4: Always open with the specific thing in 'What I noticed', and re-check it on the live site first, since sites change.
A5: No email listed? Use the 'Best contact' column: Instagram or Facebook messages work well for businesses that live on social media.
A6: Emails: include your name, business, website and an opt-out line (CASL).
A7: Sources: Alliston BIA directory (allistonbia.com/directory), Yellow Pages, Mad Barn equine directory, and each business's own website. Status checked with Bing searches on Oct 14, 2026.
A8: Removed businesses are listed on the 'Removed' tab with the reason.

Sheet Targets
A1: Priority | B1: Business | C1: Type | D1: Address | E1: Website | F1: What I noticed (use in your opener) | G1: Email | H1: Phone | I1: Best contact | J1: Suggested offer | K1: Status | L1: Date contacted | M1: Follow up on | N1: Notes
A2: A | B2: Hooves For Heart | C2: Riding lessons / equine therapy | D2: 3-92 Victoria St E, Alliston | E2: https://hooves4heart-ca.webnode.page/ | F2: Site is on a free Webnode address, not its own domain. Closest match to your EFE project. Check the site yourself before sending. | G2: hoovesforheart@gmail.com | H2: (647) 621-6710 | I2: Email | J2: Small business site from $700 | K2: Not contacted | M2: =IF(L2="","",L2+7) | N2: EMAIL DRAFTED. Swap the 'quick chat' line for the 'send over a few free ideas' line.
A3: A | B3: Foxbury Farm | C3: Riding school & boarding | D3: 1148 10th Sideroad, Tottenham | E3: https://www.foxburyfarm.ca | F3: Homepage has leftover template wording ('vibrant energy of the area', 'ranked top Riding School time and time again'); no lesson or boarding prices; homepage doesn't show the horses or facility. | G3: info@foxburyfarm.ca | H3: 905-936-2897 | I3: Email | J3: Homepage refresh from $500 | K3: Not contacted | M3: =IF(L3="","",L3+7) | N3: EMAIL DRAFTED. Active on Instagram (@foxbury_farm) and Facebook.
A4: A | B4: Barb's Clothes Closet | C4: Clothing retail | D4: 124 Victoria St W, Alliston | E4: http://barbsclothescloset.com | F4: Footer still says (c) 2019; Google search description says 35 years but the site says 41; duplicated menus and empty partner-logo images. | G4: barbsclothescloset@gmail.com | H4: 705-435-9895 | I4: Email | J4: Homepage refresh from $500 | K4: Not contacted | M4: =IF(L4="","",L4+7) | N4: EMAIL DRAFTED. Check the Google listing text before sending.
A5: A | B5: Fire & Ice Goldsmithing | C5: Jeweller (Joe Casiello) | D5: 36 Victoria St W, Alliston | E5: https://www.fireandicegoldsmithing.com | F5: Weebly site; contact page has no shop address or hours; 'Get in ToucH WITH US' capitalization; 'Powered by Weebly' banner. | G5: joe-fire-ice@hotmail.com | H5: 416-559-0357 | I5: Email | J5: Small business site from $700 | K5: Not contacted | M5: =IF(L5="","",L5+7) | N5: EMAIL DRAFTED.
A6: A | B6: Table For 2 Steakhouse | C6: Restaurant | D6: 49 Victoria St W, Alliston | E6: https://tablefor2.ca | F6: Main heading repeats 3 times; 'Weekly Promotions' has 5 empty bullets; reservations say 'still setting up OpenTable'; menu typos (e.g. 'gilled'). Busy, 4.6 stars on Tripadvisor. | H6: 705-250-3400 | I6: Phone | J6: Homepage refresh from $500 | K6: Not contacted | M6: =IF(L6="","",L6+7) | N6: No email found.
A7: A | B7: Nine Lives Boutique | C7: Consignment boutique (owner Katherine) | D7: 8 Victoria St E, Alliston | E7: http://ninelivesboutique.ca | F7: Wix site, footer (c) 2023; no phone or email on the site; 'Shop' and 'More' menu items don't link anywhere. | H7: 705-435-5382 | I7: Facebook message or phone | J7: Homepage refresh from $500 | K7: Not contacted | M7: =IF(L7="","",L7+7) | N7: Facebook: facebook.com/NineLivesBoutique (667 followers).
A8: A | B8: Mr. Komo Barbershop | C8: Barber | D8: 103 Victoria St W, Alliston | E8: None | F8: Opened about a year ago; active Instagram (977 followers) but no website. | H8: 705-434-1717 | I8: Instagram DM | J8: One-page site from $400 | K8: Not contacted | M8: =IF(L8="","",L8+7) | N8: Instagram: @mr.komobarbershop
A9: A | B9: Bake My Day | C9: Bakery | D9: 97 Victoria St W, Alliston | E9: None | F9: Active and open; uses Instagram as its website. (bmdbakery.ca is a different bakery in Alberta.) | H9: 705-250-9555 | I9: Instagram DM | J9: One-page site from $400 | K9: Not contacted | M9: =IF(L9="","",L9+7) | N9: Instagram: @bakemydayalliston. Also on Facebook.
A10: A | B10: Shear Addiction | C10: Hair salon | D10: 7126 4th Line, Tottenham | E10: None | F10: Active Facebook (888 followers, 4.8 stars from 56 reviews) but no website. | H10: 905-936-3727 | I10: Facebook message | J10: One-page site from $400 | K10: Not contacted | M10: =IF(L10="","",L10+7) | N10: Facebook: facebook.com/Shear.Addiction.hair.studio
A11: A | B11: Fox Creek Stables | C11: Trail rides | D11: 11838 County Rd 10, Stayner | E11: http://foxcreekstables.weebly.com | F11: Free Weebly address; no email, street address or social links anywhere on the site; pricing only 'from $25'. | H11: (705) 428-2257 | I11: Phone | J11: Small business site from $700 | K11: Not contacted | M11: =IF(L11="","",L11+7) | N11: EMAIL + PHONE SCRIPT DRAFTED. Ask for an email on the call. The Facebook 'Fox Creek Stables' is a different stable in Pennsylvania.
A12: B | B12: Bern's Flowers & Gifts | C12: Florist (owners Sharon & Lachlan McGurk) | D12: 122 Victoria St W, Alliston | E12: http://bernsflowers.com | F12: Teleflora/eFlorist storefront: Google+ icon, retired Google Analytics tag, '#' placeholder links. Just celebrated 50 years and already pays for marketing, so a harder sell. | G12: info@bernsflowers.com | H12: 705-435-5519 | I12: Email | J12: Homepage refresh from $500 | K12: Not contacted | M12: =IF(L12="","",L12+7)
A13: B | B13: Bodies in Balance Massage | C13: Massage therapy | D13: 1 Victoria St E, Alliston | E13: http://bodiesinbalance.ca | F13: Site is fairly current ((c) 2025) but has no online booking, blank search descriptions and a duplicated menu. | G13: info@bodiesinbalance.ca | H13: 705-435-5566 | I13: Email | J13: Website care from $60/mo | K13: Not contacted | M13: =IF(L13="","",L13+7)
A14: Goodwill | B14: Northern Blush Floral | C14: Florist (owner Cait Bolton) | D14: 96 Victoria St W Unit 4, Alliston | E14: https://northernblushfloral.ca | F14: Website is in good shape. Their BIA directory listing links to a misspelled domain ('nothern') and an old phone number (705-250-0428). | G14: northernblushfloral@gmail.com | H14: 647-678-2248 | I14: Email | J14: None, goodwill only | K14: Not contacted | M14: =IF(L14="","",L14+7) | N14: EMAIL DRAFTED (BIA heads-up, firefighter intro). Not a sales pitch.
A15: C | B15: Fernwood Landscaping | C15: Landscaping | D15: 134 Victoria St E, Alliston | E15: None | F15: Only old directory listings; no reviews, social media or recent activity. May not be operating. | H15: 705-435-7771 | I15: Phone | J15: One-page site from $400 | K15: Not contacted | M15: =IF(L15="","",L15+7)
A16: C | B16: Kowalski Landscaping | C16: Landscaping | D16: Alliston | E16: None | F16: Only old directory listings. May not be operating. | H16: 705-435-7670 | I16: Phone | J16: One-page site from $400 | K16: Not contacted | M16: =IF(L16="","",L16+7)
A17: C | B17: Pattison Bros | C17: Landscaping | D17: 5583 6th Line, Tottenham | E17: None | F17: Only directory listings; no reviews or social media. | H17: 905-729-2031 | I17: Phone | J17: One-page site from $400 | K17: Not contacted | M17: =IF(L17="","",L17+7)
A18: C | B18: Silver Snips | C18: Hair salon | D18: 5515 Scotch Line, Alliston | E18: None | F18: Only old directory listings. May not be operating. | H18: 705-434-4003 | I18: Phone | J18: One-page site from $400 | K18: Not contacted | M18: =IF(L18="","",L18+7)
A19: C | B19: DeMaria Coiffure | C19: Hair salon | D19: 77 Victoria St W, Alliston | E19: None | F19: Only directory listings; no reviews or social media. | H19: 705-435-5781 | I19: Phone | J19: One-page site from $400 | K19: Not contacted | M19: =IF(L19="","",L19+7)
A20: C | B20: Elegante Hair Design | C20: Hair salon | D20: 29 Paris St, Alliston (listings conflict) | E20: None | F20: Listings conflict: Alliston vs Tottenham, two phone numbers (705-250-0772 / 905-936-9182). May have moved or closed. | H20: 705-250-0772 | I20: Phone | J20: One-page site from $400 | K20: Not contacted | M20: =IF(L20="","",L20+7)
A21: C | B21: Avantgarde Hair | C21: Hair salon | D21: 19 Queen St S, Tottenham (or 4 Mill St E) | E21: None | F21: Old listings (one dated 2014) and a conflicting address. Unclear if open. | H21: 905-936-9654 | I21: Phone | J21: One-page site from $400 | K21: Not contacted | M21: =IF(L21="","",L21+7)
A22: C | B22: Pommele Acres | C22: Event barn | D22: 7018 4th Line, Tottenham | E22: None | F22: Only an Eventing Canada directory listing; no website or recent activity found. | H22: 905-936-2343 | I22: Phone | J22: One-page site from $400 | K22: Not contacted | M22: =IF(L22="","",L22+7)

Sheet Summary
A1: Outreach summary
A3: Status | B3: Count
A4: Not contacted | B4: =COUNTIF(Targets!$K$2:$K$22,A4) -> 21
A5: Contacted | B5: =COUNTIF(Targets!$K$2:$K$22,A5) -> 0
A6: Followed up | B6: =COUNTIF(Targets!$K$2:$K$22,A6) -> 0
A7: Replied | B7: =COUNTIF(Targets!$K$2:$K$22,A7) -> 0
A8: Call booked | B8: =COUNTIF(Targets!$K$2:$K$22,A8) -> 0
A9: Quoted | B9: =COUNTIF(Targets!$K$2:$K$22,A9) -> 0
A10: Won | B10: =COUNTIF(Targets!$K$2:$K$22,A10) -> 0
A11: Not interested | B11: =COUNTIF(Targets!$K$2:$K$22,A11) -> 0
A12: Total | B12: =SUM(B4:B11) -> 21
A13: Reply rate (of contacted) | B13: =IF(B12-B4=0,"-",SUM(B7:B11)/(B12-B4)) -> -

Sheet Removed
A1: Business | B1: Reason
A2: Park Lane Ranch | B2: Permanently closed
A3: Sher-al Farm | B3: Permanently closed
A4: Springland Riding Stable | B4: Permanently closed
A5: LandJ Stables | B5: Website down; only old directory listings
A6: Alliston's Attic | B6: Volunteer-run thrift store raising money for a school; not a fit
A7: Hill-Billy Hack Riding Stables | B7: News story suggests it is now an animal sanctuary
A8: Van Well Stables | B8: In Caledonia, near Hamilton; too far
A9: East Bay Riding Academy | B9: US business; old domain now redirects to a spam site
